ml-gen-alg/__init__.py
ml-gen-alg/ga.py
ml_gen_alg/__init__.py
ml_gen_alg/ga.py
ml_gen_alg/functions/__init__.py
ml_gen_alg/functions/operations.py
ml_gen_alg-1.1.3.dist-info/METADATA
ml_gen_alg-1.1.3.dist-info/WHEEL
ml_gen_alg-1.1.3.dist-info/top_level.txt
ml_gen_alg-1.1.3.dist-info/RECORD
