Metadata-Version: 2.4
Name: ml-gen-alg
Version: 1.1.3
Summary: Una librería de algoritmos genéticos en Python
Home-page: https://github.com/YFQG/ml-gen-alg
Author: Nicolas Torres & Yamid Quiroga
Author-email: nicolasrodriguezt@ucundinamarca.edu.co, yfquiroga@ucundinamarca.edu.co
Classifier: Programming Language :: Python :: 3
Classifier: License :: OSI Approved :: MIT License
Classifier: Operating System :: OS Independent
Requires-Python: >=3.7
Requires-Dist: setuptools
Requires-Dist: wheel
Requires-Dist: twine
Requires-Dist: matplotlib
Dynamic: author
Dynamic: author-email
Dynamic: classifier
Dynamic: description
Dynamic: description-content-type
Dynamic: home-page
Dynamic: requires-dist
Dynamic: requires-python
Dynamic: summary
